[
	{
		"__TYPE__": "SharedSliceContent",
		"variation": "default",
		"primary": {
			"title": {
				"__TYPE__": "FieldContent",
				"value": "eventually",
				"type": "Text"
			},
			"buttons": {
				"__TYPE__": "RepeatableContent",
				"type": "Link",
				"value": [
					{
						"key": "18036bb2-f825-4dbe-9ec9-f6526947a295",
						"__TYPE__": "LinkContent",
						"value": {
							"__TYPE__": "ExternalLink",
							"url": "http://twitter.com",
							"text": "upon",
							"variant": "tertiary"
						}
					}
				]
			}
		},
		"items": []
	}
]